MANIFEST.in
README.rst
setup.py
onlinekx/__init__.py
onlinekx/command_line.py
onlinekx.egg-info/PKG-INFO
onlinekx.egg-info/SOURCES.txt
onlinekx.egg-info/dependency_links.txt
onlinekx.egg-info/entry_points.txt
onlinekx.egg-info/not-zip-safe
onlinekx.egg-info/requires.txt
onlinekx.egg-info/top_level.txt